google/cloud/firestore/__init__.py
google/cloud/firestore/gapic_version.py
google/cloud/firestore_admin_v1/__init__.py
google/cloud/firestore_admin_v1/gapic_metadata.json
google/cloud/firestore_admin_v1/gapic_version.py
google/cloud/firestore_admin_v1/py.typed
google/cloud/firestore_admin_v1/services/__init__.py
google/cloud/firestore_admin_v1/services/firestore_admin/__init__.py
google/cloud/firestore_admin_v1/services/firestore_admin/async_client.py
google/cloud/firestore_admin_v1/services/firestore_admin/client.py
google/cloud/firestore_admin_v1/services/firestore_admin/pagers.py
google/cloud/firestore_admin_v1/services/firestore_admin/transports/__init__.py
google/cloud/firestore_admin_v1/services/firestore_admin/transports/base.py
google/cloud/firestore_admin_v1/services/firestore_admin/transports/grpc.py
google/cloud/firestore_admin_v1/services/firestore_admin/transports/grpc_asyncio.py
google/cloud/firestore_admin_v1/services/firestore_admin/transports/rest.py
google/cloud/firestore_admin_v1/types/__init__.py
google/cloud/firestore_admin_v1/types/backup.py
google/cloud/firestore_admin_v1/types/database.py
google/cloud/firestore_admin_v1/types/field.py
google/cloud/firestore_admin_v1/types/firestore_admin.py
google/cloud/firestore_admin_v1/types/index.py
google/cloud/firestore_admin_v1/types/location.py
google/cloud/firestore_admin_v1/types/operation.py
google/cloud/firestore_admin_v1/types/schedule.py
google/cloud/firestore_bundle/__init__.py
google/cloud/firestore_bundle/_helpers.py
google/cloud/firestore_bundle/bundle.py
google/cloud/firestore_bundle/gapic_metadata.json
google/cloud/firestore_bundle/gapic_version.py
google/cloud/firestore_bundle/py.typed
google/cloud/firestore_bundle/services/__init__.py
google/cloud/firestore_bundle/types/__init__.py
google/cloud/firestore_bundle/types/bundle.py
google/cloud/firestore_v1/__init__.py
google/cloud/firestore_v1/_helpers.py
google/cloud/firestore_v1/aggregation.py
google_cloud_firestore-2.20.0.dist-info/LICENSE
google_cloud_firestore-2.20.0.dist-info/METADATA
google_cloud_firestore-2.20.0.dist-info/WHEEL
google_cloud_firestore-2.20.0.dist-info/top_level.txt
google_cloud_firestore-2.20.0.dist-info/RECORD
